LICENSE
README.md
setup.py
pyipma/__init__.py
pyipma/api.py
pyipma/auxiliar.py
pyipma/dico_codes.py
pyipma/forecast.py
pyipma/location.py
pyipma/observation.py
pyipma/rcm.py
pyipma/sea_forecast.py
pyipma/uv.py
pyipma/warnings.py
pyipma.egg-info/PKG-INFO
pyipma.egg-info/SOURCES.txt
pyipma.egg-info/dependency_links.txt
pyipma.egg-info/requires.txt
pyipma.egg-info/top_level.txt
pyipma.egg-info/zip-safe