Metadata-Version: 2.1
Name: pyipma
Version: 3.0.8
Summary: Python library to retrieve information from Instituto Português do Mar e Atmosfera.
Home-page: https://github.com/dgomes/pyipma
Author: Diogo Gomes
Author-email: diogogomes@gmail.com
License: MIT License
Platform: any
Classifier: License :: OSI Approved :: MIT License
Classifier: Intended Audience :: Developers
Classifier: Operating System :: OS Independent
Classifier: Programming Language :: Python
Classifier: Programming Language :: Python :: 3
Classifier: Topic :: Software Development :: Libraries :: Python Modules
License-File: LICENSE
